llm_digitalocean.py
llm_digitalocean-0.1.0.dist-info/METADATA
llm_digitalocean-0.1.0.dist-info/WHEEL
llm_digitalocean-0.1.0.dist-info/entry_points.txt
llm_digitalocean-0.1.0.dist-info/top_level.txt
llm_digitalocean-0.1.0.dist-info/RECORD
