Metadata-Version: 2.4
Name: llm-digitalocean
Version: 0.1.0
Summary: LLM plugin for models hosted by DigitalOcean AI
Author: Rajashekar Chintalapti
License-Expression: Apache-2.0
Project-URL: Homepage, https://github.com/rajashekar/llm-digitalocean
Project-URL: Changelog, https://github.com/rajashekar/llm-digitalocean/releases
Project-URL: Issues, https://github.com/rajashekar/llm-digitalocean/issues
Project-URL: CI, https://github.com/rajashekar/llm-digitalocean/actions
Keywords: llm,ai,digitalocean,language-models,plugin
Classifier: Development Status :: 3 - Alpha
Classifier: Intended Audience :: Developers
Classifier: Programming Language :: Python :: 3
Classifier: Programming Language :: Python :: 3.9
Classifier: Programming Language :: Python :: 3.10
Classifier: Programming Language :: Python :: 3.11
Classifier: Programming Language :: Python :: 3.12
Classifier: Programming Language :: Python :: 3.13
Classifier: Topic :: Software Development :: Libraries :: Python Modules
Requires-Python: >=3.9
Requires-Dist: llm>=0.23
Requires-Dist: httpx
Requires-Dist: openai>=1.57.0
Provides-Extra: test
Requires-Dist: pytest; extra == "test"
Requires-Dist: pytest-recording; extra == "test"
Requires-Dist: inline-snapshot; extra == "test"
Provides-Extra: lint
Requires-Dist: flake8; extra == "lint"
Requires-Dist: black; extra == "lint"
Requires-Dist: isort; extra == "lint"
